odoo/addons/ddmrp_sale/README.rst
odoo/addons/ddmrp_sale/__init__.py
odoo/addons/ddmrp_sale/__manifest__.py
odoo/addons/ddmrp_sale/i18n/ddmrp_sale.pot
odoo/addons/ddmrp_sale/i18n/es.po
odoo/addons/ddmrp_sale/i18n/it.po
odoo/addons/ddmrp_sale/i18n/tr.po
odoo/addons/ddmrp_sale/i18n/tr_TR.po
odoo/addons/ddmrp_sale/models/__init__.py
odoo/addons/ddmrp_sale/models/stock_buffer.py
odoo/addons/ddmrp_sale/readme/CONTRIBUTORS.rst
odoo/addons/ddmrp_sale/readme/DESCRIPTION.rst
odoo/addons/ddmrp_sale/readme/HISTORY.rst
odoo/addons/ddmrp_sale/static/description/icon.png
odoo/addons/ddmrp_sale/static/description/index.html
odoo/addons/ddmrp_sale/tests/__init__.py
odoo/addons/ddmrp_sale/tests/test_ddmrp_sale.py
odoo/addons/ddmrp_sale/views/stock_buffer_view.xml
odoo_addon_ddmrp_sale-16.0.1.0.0.8.dist-info/METADATA
odoo_addon_ddmrp_sale-16.0.1.0.0.8.dist-info/WHEEL
odoo_addon_ddmrp_sale-16.0.1.0.0.8.dist-info/top_level.txt
odoo_addon_ddmrp_sale-16.0.1.0.0.8.dist-info/RECORD
